karrio/server/conf.py
karrio/server/openapi.py
karrio/server/samples.py
karrio/server/core/__init__.py
karrio/server/core/admin.py
karrio/server/core/apps.py
karrio/server/core/authentication.py
karrio/server/core/config.py
karrio/server/core/context_processors.py
karrio/server/core/datatypes.py
karrio/server/core/dataunits.py
karrio/server/core/exceptions.py
karrio/server/core/fields.py
karrio/server/core/filters.py
karrio/server/core/gateway.py
karrio/server/core/logging.py
karrio/server/core/middleware.py
karrio/server/core/oauth_validators.py
karrio/server/core/permissions.py
karrio/server/core/renderers.py
karrio/server/core/router.py
karrio/server/core/serializers.py
karrio/server/core/signals.py
karrio/server/core/telemetry.py
karrio/server/core/urls.py
karrio/server/core/utils.py
karrio/server/core/validators.py
karrio/server/core/management/commands/cli.py
karrio/server/core/management/commands/create_oauth_client.py
karrio/server/core/management/commands/runserver.py
karrio/server/core/migrations/0001_initial.py
karrio/server/core/migrations/0002_apilogindex.py
karrio/server/core/migrations/0003_apilogindex_test_mode.py
karrio/server/core/migrations/0004_metafield.py
karrio/server/core/migrations/0005_alter_metafield_type_alter_metafield_value.py
karrio/server/core/migrations/0006_add_api_log_requested_at_index.py
karrio/server/core/migrations/0007_add_generic_fk_to_metafield.py
karrio/server/core/migrations/__init__.py
karrio/server/core/models/__init__.py
karrio/server/core/models/base.py
karrio/server/core/models/entity.py
karrio/server/core/models/metafield.py
karrio/server/core/models/third_party.py
karrio/server/core/tests/__init__.py
karrio/server/core/tests/base.py
karrio/server/core/tests/test_exception_level.py
karrio/server/core/tests/test_resource_token.py
karrio/server/core/views/__init__.py
karrio/server/core/views/api.py
karrio/server/core/views/metadata.py
karrio/server/core/views/oauth.py
karrio/server/core/views/references.py
karrio_server_core-2026.1.4.dist-info/METADATA
karrio_server_core-2026.1.4.dist-info/WHEEL
karrio_server_core-2026.1.4.dist-info/top_level.txt
karrio_server_core-2026.1.4.dist-info/RECORD
