Metadata-Version: 2.4
Name: karrio_server_core
Version: 2026.1.4
Summary: Multi-carrier shipping API Core module
Author-email: karrio <hello@karrio.io>
License-Expression: LGPL-3.0
Project-URL: Homepage, https://github.com/karrioapi/karrio
Classifier: Programming Language :: Python :: 3
Requires-Python: >=3.11
Requires-Dist: karrio
Requires-Dist: psycopg2-binary
Requires-Dist: django-health-check
Requires-Dist: psutil
Requires-Dist: pyyaml
Requires-Dist: Jinja2
